src/__init__.py
src/__main__.py
src/app.py
src/field.py
src/output.py
src/settings.py
src/task.py
src/elliptic/__init__.py
src/elliptic/elliptic.py
src/elliptic/errors.py
src/parser/__init__.py
src/parser/common.py
src/parser/errors.py
src/parser/input_stream.py
src/parser/polynomial.py
src/polynomial/__init__.py
src/polynomial/errors.py
src/polynomial/irreducible.py
src/polynomial/polynomial.py
src/polynomial/utils.py
elliptic_curve-0.1.2.dist-info/METADATA
elliptic_curve-0.1.2.dist-info/WHEEL
elliptic_curve-0.1.2.dist-info/entry_points.txt
elliptic_curve-0.1.2.dist-info/top_level.txt
elliptic_curve-0.1.2.dist-info/RECORD
