Metadata-Version: 2.1
Name: elliptic-curve
Version: 0.1.2
Summary: Учебный проект для сложения точек эллиптической кривой
Home-page: UNKNOWN
Author: d4n13lzh3
Author-email: zhe.dan28@gmail.com
License: UNKNOWN
Platform: all
Classifier: Intended Audience :: Developers
Classifier: Natural Language :: Russian
Classifier: Operating System :: MacOS
Classifier: Operating System :: POSIX
Classifier: Programming Language :: Python
Classifier: Programming Language :: Python :: 3
Classifier: Programming Language :: Python :: 3.8
Classifier: Programming Language :: Python :: Implementation :: CPython
Requires-Python: >=3.7
Provides-Extra: dev
Requires-Dist: pre-commit (==2.9.2) ; extra == 'dev'
Requires-Dist: coverage (==5.3) ; extra == 'dev'
Requires-Dist: pytest (==6.1.2) ; extra == 'dev'
Requires-Dist: pytest-pythonpath (==0.7.3) ; extra == 'dev'
